stutter_string/__about__.py
stutter_string/__init__.py
stutter_string-1.0.1.dist-info/METADATA
stutter_string-1.0.1.dist-info/WHEEL
stutter_string-1.0.1.dist-info/licenses/LICENSE.txt
stutter_string-1.0.1.dist-info/RECORD
